composable/__init__.py
composable/dict.py
composable/glob.py
composable/maybe.py
composable/object.py
composable/operator.py
composable/origami.py
composable/pipeable.py
composable/records.py
composable/sequence.py
composable/strict.py
composable/string.py
composable/tox.ini
composable/try_.py
composable/tuple.py
composable/tuples.py
composable/utility.py
composable-1.3.0.dist-info/METADATA
composable-1.3.0.dist-info/WHEEL
composable-1.3.0.dist-info/RECORD
