Metadata-Version: 2.3
Name: composable
Version: 1.3.0
Summary: Callable functions that be composed/piped using >> and <<
License: MIT
Author: Todd Iverson
Author-email: tiverson@winona.edu
Requires-Python: >=3.9
Classifier: License :: OSI Approved :: MIT License
Classifier: Programming Language :: Python :: 3
Classifier: Programming Language :: Python :: 3.9
Classifier: Programming Language :: Python :: 3.10
Classifier: Programming Language :: Python :: 3.11
Classifier: Programming Language :: Python :: 3.12
Classifier: Programming Language :: Python :: 3.13
Requires-Dist: toolz (>=0.11.1)
